ardent/__init__.py
ardent/client.py
ardent/configs_values.py
ardent/exceptions.py
ardent_sdk-0.3.7.dist-info/licenses/LICENSE
tests/__init__.py
tests/test_client.py
ardent_sdk-0.3.7.dist-info/METADATA
ardent_sdk-0.3.7.dist-info/WHEEL
ardent_sdk-0.3.7.dist-info/top_level.txt
ardent_sdk-0.3.7.dist-info/RECORD
